<?xml version='1.0' encoding='utf-8'?>
<!-- FreeCAD DocumentObject -->
<Document SchemaVersion="4" FileVersion="2">
<Object name="Sketch002" Extensions="True">
  <Extensions Count="1">
    <Extension type="Part::AttachExtension" name="AttachExtension">
    </Extension>
  </Extensions>
  <Properties Count="19" TransientCount="1">
    <_Property name="_ElementMapVersion" type="App::PropertyString" status="234881024"/>
    <Property name="AttacherType" type="App::PropertyString" status="8">
      <String value="Attacher::AttachEnginePlane"/>
    </Property>
    <Property name="AttachmentOffset" type="App::PropertyPlacement">
      <PropertyPlacement Px="0" Py="0" Pz="0" Q0="0" Q1="0" Q2="0" Q3="1" A="0" Ox="0" Oy="0" Oz="1"/>
    </Property>
    <Property name="ColoredElements" type="App::PropertyLinkSubHidden" status="218103808">
      <LinkSub value="" count="0">
      </LinkSub>
    </Property>
    <Property name="Constraints" type="Sketcher::PropertyConstraintList">
      <ConstraintList count="22">
        <Constrain Name="" Type="1" Value="0" First="0" FirstPos="2" Second="1" SecondPos="1" Third="-2000" ThirdPos="0" LabelDistance="10" LabelPosition="0" IsDriving="1" IsInVirtualSpace="0" IsActive="1" />
        <Constrain Name="" Type="1" Value="0" First="1" FirstPos="2" Second="2" SecondPos="1" Third="-2000" ThirdPos="0" LabelDistance="10" LabelPosition="0" IsDriving="1" IsInVirtualSpace="0" IsActive="1" />
        <Constrain Name="" Type="1" Value="0" First="2" FirstPos="2" Second="3" SecondPos="1" Third="-2000" ThirdPos="0" LabelDistance="10" LabelPosition="0" IsDriving="1" IsInVirtualSpace="0" IsActive="1" />
        <Constrain Name="" Type="1" Value="0" First="3" FirstPos="2" Second="4" SecondPos="1" Third="-2000" ThirdPos="0" LabelDistance="10" LabelPosition="0" IsDriving="1" IsInVirtualSpace="0" IsActive="1" />
        <Constrain Name="" Type="1" Value="0" First="4" FirstPos="2" Second="5" SecondPos="1" Third="-2000" ThirdPos="0" LabelDistance="10" LabelPosition="0" IsDriving="1" IsInVirtualSpace="0" IsActive="1" />
        <Constrain Name="" Type="1" Value="0" First="5" FirstPos="2" Second="0" SecondPos="1" Third="-2000" ThirdPos="0" LabelDistance="10" LabelPosition="0" IsDriving="1" IsInVirtualSpace="0" IsActive="1" />
        <Constrain Name="" Type="12" Value="0" First="0" FirstPos="0" Second="1" SecondPos="0" Third="-2000" ThirdPos="0" LabelDistance="10" LabelPosition="0" IsDriving="1" IsInVirtualSpace="0" IsActive="1" />
        <Constrain Name="" Type="12" Value="0" First="0" FirstPos="0" Second="2" SecondPos="0" Third="-2000" ThirdPos="0" LabelDistance="10" LabelPosition="0" IsDriving="1" IsInVirtualSpace="0" IsActive="1" />
        <Constrain Name="" Type="12" Value="0" First="0" FirstPos="0" Second="3" SecondPos="0" Third="-2000" ThirdPos="0" LabelDistance="10" LabelPosition="0" IsDriving="1" IsInVirtualSpace="0" IsActive="1" />
        <Constrain Name="" Type="12" Value="0" First="0" FirstPos="0" Second="4" SecondPos="0" Third="-2000" ThirdPos="0" LabelDistance="10" LabelPosition="0" IsDriving="1" IsInVirtualSpace="0" IsActive="1" />
        <Constrain Name="" Type="12" Value="0" First="0" FirstPos="0" Second="5" SecondPos="0" Third="-2000" ThirdPos="0" LabelDistance="10" LabelPosition="0" IsDriving="1" IsInVirtualSpace="0" IsActive="1" />
        <Constrain Name="" Type="13" Value="0" First="0" FirstPos="2" Second="6" SecondPos="0" Third="-2000" ThirdPos="0" LabelDistance="10" LabelPosition="0" IsDriving="1" IsInVirtualSpace="0" IsActive="1" />
        <Constrain Name="" Type="13" Value="0" First="1" FirstPos="2" Second="6" SecondPos="0" Third="-2000" ThirdPos="0" LabelDistance="10" LabelPosition="0" IsDriving="1" IsInVirtualSpace="0" IsActive="1" />
        <Constrain Name="" Type="13" Value="0" First="2" FirstPos="2" Second="6" SecondPos="0" Third="-2000" ThirdPos="0" LabelDistance="10" LabelPosition="0" IsDriving="1" IsInVirtualSpace="0" IsActive="1" />
        <Constrain Name="" Type="13" Value="0" First="3" FirstPos="2" Second="6" SecondPos="0" Third="-2000" ThirdPos="0" LabelDistance="10" LabelPosition="0" IsDriving="1" IsInVirtualSpace="0" IsActive="1" />
        <Constrain Name="" Type="13" Value="0" First="4" FirstPos="2" Second="6" SecondPos="0" Third="-2000" ThirdPos="0" LabelDistance="10" LabelPosition="0" IsDriving="1" IsInVirtualSpace="0" IsActive="1" />
        <Constrain Name="" Type="13" Value="0" First="5" FirstPos="2" Second="6" SecondPos="0" Third="-2000" ThirdPos="0" LabelDistance="10" LabelPosition="0" IsDriving="1" IsInVirtualSpace="0" IsActive="1" />
        <Constrain Name="" Type="1" Value="0" First="6" FirstPos="3" Second="-1" SecondPos="1" Third="-2000" ThirdPos="0" LabelDistance="10" LabelPosition="0" IsDriving="1" IsInVirtualSpace="0" IsActive="1" />
        <Constrain Name="" Type="13" Value="0" First="5" FirstPos="2" Second="-1" SecondPos="0" Third="-2000" ThirdPos="0" LabelDistance="10" LabelPosition="0" IsDriving="1" IsInVirtualSpace="0" IsActive="1" />
        <Constrain Name="" Type="8" Value="6" First="4" FirstPos="2" Second="0" SecondPos="2" Third="-2000" ThirdPos="0" LabelDistance="3.911689519882202" LabelPosition="-6.871981620788574" IsDriving="1" IsInVirtualSpace="0" IsActive="1" />
        <Constrain Name="" Type="1" Value="0" First="7" FirstPos="3" Second="-1" SecondPos="1" Third="-2000" ThirdPos="0" LabelDistance="10" LabelPosition="0" IsDriving="1" IsInVirtualSpace="0" IsActive="1" />
        <Constrain Name="" Type="11" Value="9" First="7" FirstPos="0" Second="-2000" SecondPos="0" Third="-2000" ThirdPos="0" LabelDistance="4.556482791900635" LabelPosition="-0.5500046014785767" IsDriving="1" IsInVirtualSpace="0" IsActive="1" />
      </ConstraintList>
    </Property>
    <Property name="Exports" type="App::PropertyLinkListHidden" status="67108864">
      <LinkList count="0">
      </LinkList>
    </Property>
    <Property name="ExpressionEngine" type="App::PropertyExpressionEngine" status="67108864">
      <ExpressionEngine count="2" cdata="1">
        <Expressions><![CDATA[
0:.Constraints[19]
0:Spreadsheet.SW
0:

0:.Constraints[21]
0:Spreadsheet.l3
0:

]]>
        </Expressions>
      </ExpressionEngine>
    </Property>
    <Property name="ExternalGeo" type="Part::PropertyGeometryList" status="67108864">
      <GeometryList count="2">
        <Geometry type="Part::GeomLineSegment" id="-1" migrated="1">
          <GeoExtensions count="2">
            <GeoExtension type="Sketcher::SketchGeometryExtension" id="-1" internalGeometryType="0" geometryModeFlags="00000000000000000000000000000010"/>
            <GeoExtension type="Sketcher::ExternalGeometryExtension" Ref="" Flags="0"/>
          </GeoExtensions>
          <LineSegment StartX="0" StartY="0" StartZ="0" EndX="1" EndY="0" EndZ="0"/>
          <Construction value="1"/>
        </Geometry>
        <Geometry type="Part::GeomLineSegment" id="-2" migrated="1">
          <GeoExtensions count="2">
            <GeoExtension type="Sketcher::SketchGeometryExtension" id="-2" internalGeometryType="0" geometryModeFlags="00000000000000000000000000000010"/>
            <GeoExtension type="Sketcher::ExternalGeometryExtension" Ref="" Flags="0"/>
          </GeoExtensions>
          <LineSegment StartX="0" StartY="0" StartZ="0" EndX="0" EndY="1" EndZ="0"/>
          <Construction value="1"/>
        </Geometry>
      </GeometryList>
    </Property>
    <Property name="ExternalGeometry" type="App::PropertyLinkSubList" status="16777216">
      <LinkSubList count="0">
      </LinkSubList>
    </Property>
    <Property name="FullyConstrained" type="App::PropertyBool" status="218103808">
      <Bool value="true"/>
    </Property>
    <Property name="Geometry" type="Part::PropertyGeometryList" status="8192">
      <GeometryList count="8">
        <Geometry type="Part::GeomLineSegment" id="32" migrated="1">
          <GeoExtensions count="1">
            <GeoExtension type="Sketcher::SketchGeometryExtension" id="32" internalGeometryType="0" geometryModeFlags="00000000000000000000000000000000"/>
          </GeoExtensions>
          <LineSegment StartX="3.464101615137754" StartY="0" StartZ="0" EndX="1.732050807568877" EndY="3" EndZ="0"/>
          <Construction value="0"/>
        </Geometry>
        <Geometry type="Part::GeomLineSegment" id="33" migrated="1">
          <GeoExtensions count="1">
            <GeoExtension type="Sketcher::SketchGeometryExtension" id="33" internalGeometryType="0" geometryModeFlags="00000000000000000000000000000000"/>
          </GeoExtensions>
          <LineSegment StartX="1.732050807568877" StartY="3" StartZ="0" EndX="-1.732050807568878" EndY="3" EndZ="0"/>
          <Construction value="0"/>
        </Geometry>
        <Geometry type="Part::GeomLineSegment" id="34" migrated="1">
          <GeoExtensions count="1">
            <GeoExtension type="Sketcher::SketchGeometryExtension" id="34" internalGeometryType="0" geometryModeFlags="00000000000000000000000000000000"/>
          </GeoExtensions>
          <LineSegment StartX="-1.732050807568878" StartY="3" StartZ="0" EndX="-3.464101615137755" EndY="4.440892098500626e-16" EndZ="0"/>
          <Construction value="0"/>
        </Geometry>
        <Geometry type="Part::GeomLineSegment" id="35" migrated="1">
          <GeoExtensions count="1">
            <GeoExtension type="Sketcher::SketchGeometryExtension" id="35" internalGeometryType="0" geometryModeFlags="00000000000000000000000000000000"/>
          </GeoExtensions>
          <LineSegment StartX="-3.464101615137755" StartY="4e-16" StartZ="0" EndX="-1.732050807568877" EndY="-3" EndZ="0"/>
          <Construction value="0"/>
        </Geometry>
        <Geometry type="Part::GeomLineSegment" id="36" migrated="1">
          <GeoExtensions count="1">
            <GeoExtension type="Sketcher::SketchGeometryExtension" id="36" internalGeometryType="0" geometryModeFlags="00000000000000000000000000000000"/>
          </GeoExtensions>
          <LineSegment StartX="-1.732050807568877" StartY="-3" StartZ="0" EndX="1.732050807568877" EndY="-3" EndZ="0"/>
          <Construction value="0"/>
        </Geometry>
        <Geometry type="Part::GeomLineSegment" id="37" migrated="1">
          <GeoExtensions count="1">
            <GeoExtension type="Sketcher::SketchGeometryExtension" id="37" internalGeometryType="0" geometryModeFlags="00000000000000000000000000000000"/>
          </GeoExtensions>
          <LineSegment StartX="1.732050807568877" StartY="-3" StartZ="0" EndX="3.464101615137754" EndY="0" EndZ="0"/>
          <Construction value="0"/>
        </Geometry>
        <Geometry type="Part::GeomCircle" id="38" migrated="1">
          <GeoExtensions count="1">
            <GeoExtension type="Sketcher::SketchGeometryExtension" id="38" internalGeometryType="0" geometryModeFlags="00000000000000000000000000000010"/>
          </GeoExtensions>
          <Circle CenterX="0" CenterY="0" CenterZ="0" NormalX="0" NormalY="0" NormalZ="1" AngleXU="-0" Radius="3.464101615137754"/>
          <Construction value="1"/>
        </Geometry>
        <Geometry type="Part::GeomCircle" id="39" migrated="1">
          <GeoExtensions count="1">
            <GeoExtension type="Sketcher::SketchGeometryExtension" id="39" internalGeometryType="0" geometryModeFlags="00000000000000000000000000000000"/>
          </GeoExtensions>
          <Circle CenterX="0" CenterY="0" CenterZ="0" NormalX="0" NormalY="0" NormalZ="1" AngleXU="-0" Radius="9"/>
          <Construction value="0"/>
        </Geometry>
      </GeometryList>
    </Property>
    <Property name="Label" type="App::PropertyString" status="134217728">
      <String value="Sketch002"/>
    </Property>
    <Property name="Label2" type="App::PropertyString" status="128">
      <String value=""/>
    </Property>
    <Property name="MapMode" type="App::PropertyEnumeration">
      <Integer value="5"/>
    </Property>
    <Property name="MapPathParameter" type="App::PropertyFloat" status="8">
      <Float value="0"/>
    </Property>
    <Property name="MapReversed" type="App::PropertyBool">
      <Bool value="false"/>
    </Property>
    <Property name="Placement" type="App::PropertyPlacement" status="8388612">
      <PropertyPlacement Px="0" Py="0" Pz="0" Q0="0" Q1="0" Q2="0" Q3="1" A="0" Ox="0" Oy="0" Oz="1"/>
    </Property>
    <Property name="Shape" type="Part::PropertyPartShape">
      <Part ElementMap="0.15.70200.3" brep="1">
<![CDATA[

CASCADE Topology V1, (c) Matra-Datavision
Locations 8
1
              1               0               0               0 
              0               1               0               0 
              0               0               1               0 
1
              1               0               0               0 
              0               1               0 43.7109517169324 
              0               0               1          -1e-14 
1
              1               0               0               0 
              0              -0              -1               0 
              0               1              -0               0 
1
              1               0               0               0 
              0               1               0               0 
              0               0               1               0 
1
              1               0               0               0 
              0               1               0               0 
              0               0               1               0 
2  2 -1 3 1 4 -1 5 -1 0
1
              1               0               0              -0 
              0               1               0 -87.4219034338649 
              0               0               1         1.9e-14 
2  7 -1 2 -1 3 1 4 -1 5 -1 0
Curve2ds 14
1 -0 0 1 0 
1 0 -87.421903433864898 1 0 
1 0 0 1 0 
1 -0 -87.421903433864898 1 0 
1 0 0 1 0 
1 1.1e-16 -87.421903433864898 1 0 
1 0 0 1 0 
1 0 -87.421903433864898 1 0 
1 0 0 1 0 
1 -0 -87.421903433864898 1 0 
1 0 0 1 0 
1 -1.1e-16 -87.421903433864898 1 0 
1 0 0 1 0 
1 0 -87.421903433864898 1 0 
Curves 7
1 3.4641016151377544 0 0 -0.49999999999999994 0.86602540378443871 0 
1 1.7320508075688774 3 0 -1 0 0 
1 -1.7320508075688779 3 0 -0.5 -0.86602540378443871 0 
1 -3.4641016151377548 4.4e-16 0 0.50000000000000011 -0.86602540378443871 0 
1 -1.7320508075688772 -3 0 1 1.2999999999999999e-16 0 
1 1.7320508075688772 -2.9999999999999996 0 0.50000000000000011 0.86602540378443871 0 
2 0 0 0 0 0 1 1 0 -0 -0 1 0 9
Polygon3D 0
PolygonOnTriangulations 0
Surfaces 7
1 3.4641016151377544 43.710951716932449 -9.7100000000000004e-15 0.86602540378443871 -1.1e-16 -0.49999999999999994 -0.49999999999999994 -1.9000000000000003e-16 -0.86602540378443871 2.6279441628825805e-19 1 -2.1954482671904337e-16 
1 1.7320508075688774 43.710951716932449 -3.0000000000000098 0 -2.2e-16 -1 -1 0 -0 0 1 -2.2e-16 
1 -1.7320508075688779 43.710951716932449 -3.0000000000000098 -0.86602540378443871 -1.1e-16 -0.5 -0.5 1.9000000000000003e-16 0.86602540378443871 -2.6279441628824572e-19 1 -2.1954482671904339e-16 
1 -3.4641016151377548 43.710951716932449 -1.015e-14 -0.86602540378443871 1.1e-16 0.50000000000000011 0.50000000000000011 1.8999999999999998e-16 0.86602540378443871 2.6279441628824567e-19 1 -2.1954482671904329e-16 
1 -1.7320508075688772 43.710951716932449 2.9999999999999902 1.2999999999999999e-16 2.2e-16 1 1 0 -1.2999999999999999e-16 -2.86e-32 1 -2.2e-16 
1 1.7320508075688772 43.710951716932449 2.9999999999999898 0.86602540378443871 1.1e-16 0.50000000000000011 0.50000000000000011 -1.8999999999999998e-16 -0.86602540378443871 -2.6279441628824567e-19 1 -2.1954482671904329e-16 
2 0 43.710951716932449 -9.7100000000000004e-15 0 1 -2.2e-16 1 0 0 0 -2.2e-16 -1 9
Triangulations 0

TShapes 17
Ve
1e-07
3.46410161513775 0 0
0 0

0101101
*
Ve
1e-07
1.73205080756888 3 0
0 0

0101101
*
Ed
 1e-07 1 1 0
1  1 0 0 3.46410161513775
2  1 1 6 0 3.46410161513775
2  2 1 8 0 3.46410161513775
0

0101000
+17 0 -16 0 *
Ve
1e-07
-1.73205080756888 3 0
0 0

0101101
*
Ed
 1e-07 1 1 0
1  2 0 0 3.46410161513775
2  3 2 6 0 3.46410161513775
2  4 2 8 0 3.46410161513775
0

0101000
+16 0 -14 0 *
Ve
1e-07
-3.46410161513775 0 0
0 0

0101101
*
Ed
 1e-07 1 1 0
1  3 0 0 3.46410161513775
2  5 3 6 0 3.46410161513775
2  6 3 8 0 3.46410161513775
0

0101000
+14 0 -12 0 *
Ve
1e-07
-1.73205080756888 -3 0
0 0

0101101
*
Ed
 1e-07 1 1 0
1  4 0 0 3.46410161513775
2  7 4 6 0 3.46410161513775
2  8 4 8 0 3.46410161513775
0

0101000
+12 0 -10 0 *
Ve
1e-07
1.73205080756888 -3 0
0 0

0101101
*
Ed
 1e-07 1 1 0
1  5 0 0 3.46410161513775
2  9 5 6 0 3.46410161513775
2  10 5 8 0 3.46410161513775
0

0101000
+10 0 -8 0 *
Ed
 1e-07 1 1 0
1  6 0 0 3.46410161513775
2  11 6 6 0 3.46410161513775
2  12 6 8 0 3.46410161513775
0

0101000
+8 0 -17 0 *
Wi

0101100
+15 0 +13 0 +11 0 +9 0 +7 0 +6 0 *
Ve
1e-07
9 0 0
0 0

0101101
*
Ed
 1e-07 1 1 0
1  7 0 0 6.28318530717959
2  13 7 6 0 6.28318530717959
2  14 7 8 0 6.28318530717959
0

0101000
+4 0 -4 0 *
Wi

0101100
+3 0 *
Co

1100000
+5 0 +2 0 *

+1 1 ]]>
      </Part>
      <ElementMap count="20">
<![CDATA[
Edge1	g32;SKT 0
Edge2	g33;SKT 0
Edge3	g34;SKT 0
Edge4	g35;SKT 0
Edge5	g36;SKT 0
Edge6	g37;SKT 0
Edge7	g39;SKT 0
Vertex1	g32v1;SKT 0
Vertex1	g37v2;SKT 0
Vertex2	g32v2;SKT 0
Vertex2	g33v1;SKT 0
Vertex3	g33v2;SKT 0
Vertex3	g34v1;SKT 0
Vertex4	g34v2;SKT 0
Vertex4	g35v1;SKT 0
Vertex5	g35v2;SKT 0
Vertex5	g36v1;SKT 0
Vertex6	g36v2;SKT 0
Vertex6	g37v1;SKT 0
Vertex7	g39v1;SKT 0
]]>
      </ElementMap>
    </Property>
    <Property name="Support" type="App::PropertyLinkSubList">
      <LinkSubList count="1">
        <Link obj="XY_Plane002" sub=""/>
      </LinkSubList>
    </Property>
    <Property name="Visibility" type="App::PropertyBool" status="648">
      <Bool value="false"/>
    </Property>
  </Properties>
</Object>
</Document>
